sqlalchemy_pysqlite3/__init__.py
sqlalchemy_pysqlite3_binary-0.0.4.dist-info/LICENSE
sqlalchemy_pysqlite3_binary-0.0.4.dist-info/METADATA
sqlalchemy_pysqlite3_binary-0.0.4.dist-info/WHEEL
sqlalchemy_pysqlite3_binary-0.0.4.dist-info/entry_points.txt
sqlalchemy_pysqlite3_binary-0.0.4.dist-info/top_level.txt
sqlalchemy_pysqlite3_binary-0.0.4.dist-info/RECORD
