Metadata-Version: 2.1
Name: sqlalchemy-pysqlite3-binary
Version: 0.0.4
Summary: SQLAlchemy dialect to use pysqlite3 dbapi2
Home-page: https://github.com/hoehrmann/sqlalchemy-pysqlite3
Author: Bjoern Hoehrmann
Author-email: bjoern@hoehrmann.de
Classifier: Programming Language :: Python :: 3
Classifier: License :: OSI Approved :: MIT License
Classifier: Operating System :: OS Independent
Classifier: Topic :: Software Development :: Libraries :: Python Modules
License-File: LICENSE
Requires-Dist: pysqlite3-binary
Requires-Dist: sqlalchemy
